[{"id":1103030001,"id_kecamatan":"1103030","nama":"Pasi Lembang"},{"id":1103030002,"id_kecamatan":"1103030","nama":"Ujung Padang"},{"id":1103030003,"id_kecamatan":"1103030","nama":"Indra Damai"},{"id":1103030004,"id_kecamatan":"1103030","nama":"Suaq Bakong"},{"id":1103030005,"id_kecamatan":"1103030","nama":"Barat Daya"},{"id":1103030006,"id_kecamatan":"1103030","nama":"Sialang"},{"id":1103030007,"id_kecamatan":"1103030","nama":"Kapeh"},{"id":1103030008,"id_kecamatan":"1103030","nama":"Pulo Ie"},{"id":1103030009,"id_kecamatan":"1103030","nama":"Jua"},{"id":1103030010,"id_kecamatan":"1103030","nama":"Pasi Merapat"},{"id":1103030011,"id_kecamatan":"1103030","nama":"Ujung"},{"id":1103030012,"id_kecamatan":"1103030","nama":"Luar"},{"id":1103030013,"id_kecamatan":"1103030","nama":"Kedai Kandang"},{"id":1103030014,"id_kecamatan":"1103030","nama":"Rantau Binuang"},{"id":1103030015,"id_kecamatan":"1103030","nama":"Ujung Pasir"},{"id":1103030016,"id_kecamatan":"1103030","nama":"Gelumbuk"},{"id":1103030017,"id_kecamatan":"1103030","nama":"Kedai Runding"}]