[{"id":1110062001,"id_kecamatan":"1110062","nama":"Cot Trieng"},{"id":1110062002,"id_kecamatan":"1110062","nama":"Lhok Awe Awe"},{"id":1110062003,"id_kecamatan":"1110062","nama":"Cot Unoe"},{"id":1110062004,"id_kecamatan":"1110062","nama":"Cot Batee"},{"id":1110062005,"id_kecamatan":"1110062","nama":"Cot Kuta"},{"id":1110062006,"id_kecamatan":"1110062","nama":"Cot Glumpang"},{"id":1110062007,"id_kecamatan":"1110062","nama":"Glumpang Baroh"},{"id":1110062008,"id_kecamatan":"1110062","nama":"Lancok Pante Ara"},{"id":1110062009,"id_kecamatan":"1110062","nama":"Balee Kuyun"},{"id":1110062010,"id_kecamatan":"1110062","nama":"Kareung"},{"id":1110062011,"id_kecamatan":"1110062","nama":"Lancok Lancok"},{"id":1110062012,"id_kecamatan":"1110062","nama":"Cot Usibak"},{"id":1110062013,"id_kecamatan":"1110062","nama":"Kuala Raja"},{"id":1110062014,"id_kecamatan":"1110062","nama":"Ujong Blang Mesjid"},{"id":1110062015,"id_kecamatan":"1110062","nama":"Weu Jangka"},{"id":1110062016,"id_kecamatan":"1110062","nama":"Cot Lagasawa"},{"id":1110062017,"id_kecamatan":"1110062","nama":"Ujong Blang"},{"id":1110062018,"id_kecamatan":"1110062","nama":"Kuta Baro"},{"id":1110062019,"id_kecamatan":"1110062","nama":"Krueng Juli Timur"},{"id":1110062020,"id_kecamatan":"1110062","nama":"Krueng Juli Barat"}]