[{"id":1115011001,"id_kecamatan":"1115011","nama":"Kuala Teripa"},{"id":1115011002,"id_kecamatan":"1115011","nama":"Drien Tujoh"},{"id":1115011003,"id_kecamatan":"1115011","nama":"Lueng Keubeu Jagat"},{"id":1115011004,"id_kecamatan":"1115011","nama":"Kabu"},{"id":1115011005,"id_kecamatan":"1115011","nama":"Babah Lueng"},{"id":1115011006,"id_kecamatan":"1115011","nama":"Pasi Keubeu Dom"},{"id":1115011007,"id_kecamatan":"1115011","nama":"Neubok Yee Pk"},{"id":1115011008,"id_kecamatan":"1115011","nama":"Neubok Yee Pp"},{"id":1115011009,"id_kecamatan":"1115011","nama":"Mon Dua"},{"id":1115011010,"id_kecamatan":"1115011","nama":"Panton Pange"},{"id":1115011011,"id_kecamatan":"1115011","nama":"Ujong Krueng"}]