[{"id":1201071001,"id_kecamatan":"1201071","nama":"Tuhembuasi"},{"id":1201071002,"id_kecamatan":"1201071","nama":"Hilibadalu"},{"id":1201071003,"id_kecamatan":"1201071","nama":"Lauri"},{"id":1201071004,"id_kecamatan":"1201071","nama":"Hilimbana"},{"id":1201071005,"id_kecamatan":"1201071","nama":"Saetagaramba"},{"id":1201071006,"id_kecamatan":"1201071","nama":"Sogaeadu"},{"id":1201071007,"id_kecamatan":"1201071","nama":"Baruzo"},{"id":1201071008,"id_kecamatan":"1201071","nama":"Tulumbaho"},{"id":1201071009,"id_kecamatan":"1201071","nama":"Sihareo Sogaeadu"},{"id":1201071010,"id_kecamatan":"1201071","nama":"Wea-wea"},{"id":1201071011,"id_kecamatan":"1201071","nama":"Sisarahili Sogeadu"}]