[{"id":1204070010,"id_kecamatan":"1204070","nama":"Bukit Patupangan"},{"id":1204070011,"id_kecamatan":"1204070","nama":"Kedai Gedang"},{"id":1204070012,"id_kecamatan":"1204070","nama":"Sigambo Gambo"},{"id":1204070013,"id_kecamatan":"1204070","nama":"Padang Masiang"},{"id":1204070014,"id_kecamatan":"1204070","nama":"Kampung Solok"},{"id":1204070015,"id_kecamatan":"1204070","nama":"Pasar Batu Gerigis"},{"id":1204070016,"id_kecamatan":"1204070","nama":"Pasar Terandam"},{"id":1204070017,"id_kecamatan":"1204070","nama":"Kinali"},{"id":1204070018,"id_kecamatan":"1204070","nama":"Ujung Batu"},{"id":1204070019,"id_kecamatan":"1204070","nama":"Kampung Mudik"},{"id":1204070020,"id_kecamatan":"1204070","nama":"Gabungan Hasang"},{"id":1204070024,"id_kecamatan":"1204070","nama":"Aek Dakka"},{"id":1204070036,"id_kecamatan":"1204070","nama":"Bungo Tanjung"}]