[{"id":1206052001,"id_kecamatan":"1206052","nama":"Lumban Rau Tengah"},{"id":1206052002,"id_kecamatan":"1206052","nama":"Lumban Rau Timur"},{"id":1206052003,"id_kecamatan":"1206052","nama":"Lumban Rau Utara"},{"id":1206052004,"id_kecamatan":"1206052","nama":"Napajoring"},{"id":1206052005,"id_kecamatan":"1206052","nama":"Sipagabu"},{"id":1206052006,"id_kecamatan":"1206052","nama":"Liat Tondung"},{"id":1206052007,"id_kecamatan":"1206052","nama":"Batu Manumpak"},{"id":1206052008,"id_kecamatan":"1206052","nama":"Lumban Rau Tenggara"},{"id":1206052009,"id_kecamatan":"1206052","nama":"Cinta Damai"},{"id":1206052010,"id_kecamatan":"1206052","nama":"Siantarasa"}]