[{"id":1209200001,"id_kecamatan":"1209200","nama":"Parbutaran"},{"id":1209200002,"id_kecamatan":"1209200","nama":"Mayang"},{"id":1209200003,"id_kecamatan":"1209200","nama":"Dusun Pengkolan"},{"id":1209200004,"id_kecamatan":"1209200","nama":"Bosar Maligas"},{"id":1209200005,"id_kecamatan":"1209200","nama":"Boluk"},{"id":1209200006,"id_kecamatan":"1209200","nama":"Sei Mangkei"},{"id":1209200007,"id_kecamatan":"1209200","nama":"Gunung Bayu"},{"id":1209200008,"id_kecamatan":"1209200","nama":"Talun Saragih"},{"id":1209200009,"id_kecamatan":"1209200","nama":"Marihat Tanjung"},{"id":1209200010,"id_kecamatan":"1209200","nama":"Marihat Butar"},{"id":1209200011,"id_kecamatan":"1209200","nama":"Sei Torop"},{"id":1209200012,"id_kecamatan":"1209200","nama":"Adil Makmur"},{"id":1209200013,"id_kecamatan":"1209200","nama":"Teladan"},{"id":1209200014,"id_kecamatan":"1209200","nama":"Tempel Jaya"},{"id":1209200015,"id_kecamatan":"1209200","nama":"Sidomulyo"},{"id":1209200016,"id_kecamatan":"1209200","nama":"Nanggar Bayu"},{"id":1209200017,"id_kecamatan":"1209200","nama":"Mekar Rejo"}]