[{"id":1213030001,"id_kecamatan":"1213030","nama":"Telagah"},{"id":1213030002,"id_kecamatan":"1213030","nama":"Tanjung Gunung"},{"id":1213030003,"id_kecamatan":"1213030","nama":"Pekan Sawah"},{"id":1213030004,"id_kecamatan":"1213030","nama":"Belinteng"},{"id":1213030005,"id_kecamatan":"1213030","nama":"Rumah Galuh"},{"id":1213030006,"id_kecamatan":"1213030","nama":"Simpang Kuta Buluh"},{"id":1213030007,"id_kecamatan":"1213030","nama":"Gunung Ambat"},{"id":1213030008,"id_kecamatan":"1213030","nama":"Namu Ukur Selatan"},{"id":1213030009,"id_kecamatan":"1213030","nama":"Namu Ukur Utara"},{"id":1213030010,"id_kecamatan":"1213030","nama":"Durian Lingga"},{"id":1213030011,"id_kecamatan":"1213030","nama":"Pasar Viii Namo Terasi"},{"id":1213030012,"id_kecamatan":"1213030","nama":"Pasar Iv Namo Terasi"},{"id":1213030013,"id_kecamatan":"1213030","nama":"Pasar Vi Kwala Mencirim"},{"id":1213030014,"id_kecamatan":"1213030","nama":"Purwobinangun"},{"id":1213030015,"id_kecamatan":"1213030","nama":"Emplasmen Kwala Mencirim"},{"id":1213030016,"id_kecamatan":"1213030","nama":"Mekar Jaya"}]