[{"id":1371050020,"id_kecamatan":"1371050","nama":"Sawahan"},{"id":1371050028,"id_kecamatan":"1371050","nama":"Ganting Parak Gadang"},{"id":1371050029,"id_kecamatan":"1371050","nama":"Parak Gadang Timur"},{"id":1371050030,"id_kecamatan":"1371050","nama":"Kubu Marapalam"},{"id":1371050031,"id_kecamatan":"1371050","nama":"Kubu Parak Karakah"},{"id":1371050032,"id_kecamatan":"1371050","nama":"Andalas"},{"id":1371050033,"id_kecamatan":"1371050","nama":"Simpang Haru"},{"id":1371050034,"id_kecamatan":"1371050","nama":"Sawahan Timur"},{"id":1371050035,"id_kecamatan":"1371050","nama":"Jati Baru"},{"id":1371050036,"id_kecamatan":"1371050","nama":"Jati"}]