[{"id":1406041001,"id_kecamatan":"1406041","nama":"Kasikan"},{"id":1406041002,"id_kecamatan":"1406041","nama":"Rimba Beringin"},{"id":1406041003,"id_kecamatan":"1406041","nama":"Senama Nenek"},{"id":1406041004,"id_kecamatan":"1406041","nama":"Bukit Kemuning"},{"id":1406041005,"id_kecamatan":"1406041","nama":"Danau Lancang"},{"id":1406041006,"id_kecamatan":"1406041","nama":"Suka Ramai"},{"id":1406041007,"id_kecamatan":"1406041","nama":"Kusau Makmur"},{"id":1406041008,"id_kecamatan":"1406041","nama":"Sumber Sari"},{"id":1406041014,"id_kecamatan":"1406041","nama":"Talang Danto"},{"id":1406041015,"id_kecamatan":"1406041","nama":"Muara Intan"},{"id":1406041016,"id_kecamatan":"1406041","nama":"Intan Jaya"},{"id":1406041017,"id_kecamatan":"1406041","nama":"Tanah Datar"},{"id":1406041018,"id_kecamatan":"1406041","nama":"Rimba Makmur"},{"id":1406041019,"id_kecamatan":"1406041","nama":"Rimba Jaya"}]