[{"id":1409014001,"id_kecamatan":"1409014","nama":"Sei Meranti Darussalam"},{"id":1409014002,"id_kecamatan":"1409014","nama":"Akar Belingkar"},{"id":1409014003,"id_kecamatan":"1409014","nama":"Sei Meranti"},{"id":1409014004,"id_kecamatan":"1409014","nama":"Sei Tapah"},{"id":1409014005,"id_kecamatan":"1409014","nama":"Tanjung Medan"},{"id":1409014006,"id_kecamatan":"1409014","nama":"Tangga Batu"},{"id":1409014007,"id_kecamatan":"1409014","nama":"Tanjung Medan Barat"},{"id":1409014008,"id_kecamatan":"1409014","nama":"Tanjung Sari"},{"id":1409014009,"id_kecamatan":"1409014","nama":"Pondok Kresek"},{"id":1409014010,"id_kecamatan":"1409014","nama":"Perkebunan Tanjung Medan"},{"id":1409014011,"id_kecamatan":"1409014","nama":"Sri Kayangan"},{"id":1409014012,"id_kecamatan":"1409014","nama":"Tanjung Medan Utara"},{"id":1409014013,"id_kecamatan":"1409014","nama":"Bagan Nenas"}]