[{"id":1410030005,"id_kecamatan":"1410030","nama":"Repan"},{"id":1410030006,"id_kecamatan":"1410030","nama":"Penyagun"},{"id":1410030007,"id_kecamatan":"1410030","nama":"Gemala Sari"},{"id":1410030008,"id_kecamatan":"1410030","nama":"Sungai Gayung Kiri"},{"id":1410030009,"id_kecamatan":"1410030","nama":"Tanjung Medang"},{"id":1410030010,"id_kecamatan":"1410030","nama":"Teluk Samak"},{"id":1410030011,"id_kecamatan":"1410030","nama":"Tanjung Samak"},{"id":1410030012,"id_kecamatan":"1410030","nama":"Tanjung Bakau"},{"id":1410030013,"id_kecamatan":"1410030","nama":"Topang"},{"id":1410030014,"id_kecamatan":"1410030","nama":"Citra Damai"},{"id":1410030016,"id_kecamatan":"1410030","nama":"Dwi Tunggal"},{"id":1410030017,"id_kecamatan":"1410030","nama":"Wonosari"},{"id":1410030018,"id_kecamatan":"1410030","nama":"Tebun"},{"id":1410030020,"id_kecamatan":"1410030","nama":"Tanjung Gemuk"}]