[{"id":1501071001,"id_kecamatan":"1501071","nama":"Kemantan Hilir"},{"id":1501071002,"id_kecamatan":"1501071","nama":"Koto Tebat"},{"id":1501071003,"id_kecamatan":"1501071","nama":"Pondok Sungai Abu"},{"id":1501071004,"id_kecamatan":"1501071","nama":"Sungai Abu"},{"id":1501071005,"id_kecamatan":"1501071","nama":"Pungut Hilir"},{"id":1501071006,"id_kecamatan":"1501071","nama":"Pungut Tengah"},{"id":1501071007,"id_kecamatan":"1501071","nama":"Pungut Mudik"},{"id":1501071008,"id_kecamatan":"1501071","nama":"Desa Baru Sei Tutung"},{"id":1501071009,"id_kecamatan":"1501071","nama":"Sungai Tutung"},{"id":1501071010,"id_kecamatan":"1501071","nama":"Sungai Medang"},{"id":1501071013,"id_kecamatan":"1501071","nama":"Air Hangat"},{"id":1501071014,"id_kecamatan":"1501071","nama":"Kemantan Tinggi"},{"id":1501071015,"id_kecamatan":"1501071","nama":"Kemantan Agung"},{"id":1501071016,"id_kecamatan":"1501071","nama":"Kemantan Kebalai"},{"id":1501071017,"id_kecamatan":"1501071","nama":"Kemantan Darat"},{"id":1501071018,"id_kecamatan":"1501071","nama":"Sungai Deras"},{"id":1501071019,"id_kecamatan":"1501071","nama":"Simpang Empat Sungai Tutung"},{"id":1501071020,"id_kecamatan":"1501071","nama":"Kemantan Mudik"},{"id":1501071021,"id_kecamatan":"1501071","nama":"Baru Sungai Deras"},{"id":1501071022,"id_kecamatan":"1501071","nama":"Air Panas Sungai Abu"},{"id":1501071023,"id_kecamatan":"1501071","nama":"Baru Sungai Abu"},{"id":1501071024,"id_kecamatan":"1501071","nama":"Taman Jernih Sungai Tutung"},{"id":1501071025,"id_kecamatan":"1501071","nama":"Baru Sungai Medang"},{"id":1501071026,"id_kecamatan":"1501071","nama":"Baru Air Hangat"},{"id":1501071027,"id_kecamatan":"1501071","nama":"Kemantan Raya"}]