[{"id":1502052001,"id_kecamatan":"1502052","nama":"Bukit Perentak"},{"id":1502052002,"id_kecamatan":"1502052","nama":"Baru Pangkalan Jambu"},{"id":1502052003,"id_kecamatan":"1502052","nama":"Tigo Alur Pangkalan Jambu"},{"id":1502052004,"id_kecamatan":"1502052","nama":"Birun"},{"id":1502052005,"id_kecamatan":"1502052","nama":"Bunga Tanjung"},{"id":1502052006,"id_kecamatan":"1502052","nama":"Sungai Jering"},{"id":1502052007,"id_kecamatan":"1502052","nama":"Kampung Limo"},{"id":1502052008,"id_kecamatan":"1502052","nama":"Tanjung Mudo"}]