[{"id":1606041001,"id_kecamatan":"1606041","nama":"Danau Cala"},{"id":1606041002,"id_kecamatan":"1606041","nama":"Rantau Keroya"},{"id":1606041003,"id_kecamatan":"1606041","nama":"Teluk Kijing I"},{"id":1606041004,"id_kecamatan":"1606041","nama":"Tanjung Agung Barat"},{"id":1606041005,"id_kecamatan":"1606041","nama":"Tanjung Agung Timur"},{"id":1606041006,"id_kecamatan":"1606041","nama":"Tanjung Agung Utara"},{"id":1606041007,"id_kecamatan":"1606041","nama":"Purwosari"},{"id":1606041008,"id_kecamatan":"1606041","nama":"Teluk Kijing Iii"},{"id":1606041009,"id_kecamatan":"1606041","nama":"Teluk Kijing Ii"},{"id":1606041010,"id_kecamatan":"1606041","nama":"Petaling"},{"id":1606041011,"id_kecamatan":"1606041","nama":"Lais"},{"id":1606041012,"id_kecamatan":"1606041","nama":"Teluk"},{"id":1606041013,"id_kecamatan":"1606041","nama":"Epil"},{"id":1606041014,"id_kecamatan":"1606041","nama":"Tanjung Agung Selatan"},{"id":1606041015,"id_kecamatan":"1606041","nama":"Lais Utara"}]