[{"id":1706020005,"id_kecamatan":"1706020","nama":"Air Hitam"},{"id":1706020006,"id_kecamatan":"1706020","nama":"Dusun Tunggang"},{"id":1706020007,"id_kecamatan":"1706020","nama":"Air Berau"},{"id":1706020008,"id_kecamatan":"1706020","nama":"Pondok Suguh"},{"id":1706020010,"id_kecamatan":"1706020","nama":"Air Bikuk"},{"id":1706020011,"id_kecamatan":"1706020","nama":"Sinar Laut"},{"id":1706020013,"id_kecamatan":"1706020","nama":"Lubuk Bento"},{"id":1706020014,"id_kecamatan":"1706020","nama":"Pondok Kandang"},{"id":1706020022,"id_kecamatan":"1706020","nama":"Bumi Mekar Jaya"},{"id":1706020023,"id_kecamatan":"1706020","nama":"Karya Mulya"},{"id":1706020024,"id_kecamatan":"1706020","nama":"Teluk Bakung"}]