[{"id":1802050001,"id_kecamatan":"1802050","nama":"Tamansari"},{"id":1802050002,"id_kecamatan":"1802050","nama":"Campang Way Handak"},{"id":1802050003,"id_kecamatan":"1802050","nama":"Gading"},{"id":1802050004,"id_kecamatan":"1802050","nama":"Sumanda"},{"id":1802050005,"id_kecamatan":"1802050","nama":"Tanjung Agung"},{"id":1802050006,"id_kecamatan":"1802050","nama":"Babakan"},{"id":1802050007,"id_kecamatan":"1802050","nama":"Gunung Kasih"},{"id":1802050008,"id_kecamatan":"1802050","nama":"Tanjung Kemala"},{"id":1802050009,"id_kecamatan":"1802050","nama":"Binjai Wangi"},{"id":1802050010,"id_kecamatan":"1802050","nama":"Sukajadi"},{"id":1802050011,"id_kecamatan":"1802050","nama":"Rantau Tijang"},{"id":1802050012,"id_kecamatan":"1802050","nama":"Sinar Agung"},{"id":1802050013,"id_kecamatan":"1802050","nama":"Negeri Ratu"},{"id":1802050014,"id_kecamatan":"1802050","nama":"Way Jaha"},{"id":1802050015,"id_kecamatan":"1802050","nama":"Tiuh Memon"},{"id":1802050016,"id_kecamatan":"1802050","nama":"Banjar Agung Ilir"},{"id":1802050017,"id_kecamatan":"1802050","nama":"Banjar Agung Udik"},{"id":1802050018,"id_kecamatan":"1802050","nama":"Tanjung Heran"},{"id":1802050019,"id_kecamatan":"1802050","nama":"Tangkit Serdang"},{"id":1802050020,"id_kecamatan":"1802050","nama":"Way Pring"},{"id":1802050021,"id_kecamatan":"1802050","nama":"Pungkut"},{"id":1802050022,"id_kecamatan":"1802050","nama":"Sukamaju"},{"id":1802050023,"id_kecamatan":"1802050","nama":"Sukamulya"},{"id":1802050024,"id_kecamatan":"1802050","nama":"Kayu Hubi"},{"id":1802050025,"id_kecamatan":"1802050","nama":"Gunung Tiga"},{"id":1802050026,"id_kecamatan":"1802050","nama":"Way Manak"},{"id":1802050027,"id_kecamatan":"1802050","nama":"Talang Lebar"}]