[{"id":1804030001,"id_kecamatan":"1804030","nama":"Sidomukti"},{"id":1804030002,"id_kecamatan":"1804030","nama":"Karya Mukti"},{"id":1804030003,"id_kecamatan":"1804030","nama":"Sidomulyo"},{"id":1804030004,"id_kecamatan":"1804030","nama":"Sidodadi"},{"id":1804030005,"id_kecamatan":"1804030","nama":"Trimulyo"},{"id":1804030006,"id_kecamatan":"1804030","nama":"Girikarto"},{"id":1804030007,"id_kecamatan":"1804030","nama":"Hargomulyo"},{"id":1804030008,"id_kecamatan":"1804030","nama":"Wonokarto"},{"id":1804030009,"id_kecamatan":"1804030","nama":"Suko Harjo"},{"id":1804030010,"id_kecamatan":"1804030","nama":"Giri Kelopo Mulyo"},{"id":1804030011,"id_kecamatan":"1804030","nama":"Sumber Gede"},{"id":1804030012,"id_kecamatan":"1804030","nama":"Sambikarto"},{"id":1804030013,"id_kecamatan":"1804030","nama":"Sumbersari"},{"id":1804030014,"id_kecamatan":"1804030","nama":"Mekar Mulya"},{"id":1804030015,"id_kecamatan":"1804030","nama":"Mekar Mukti"},{"id":1804030016,"id_kecamatan":"1804030","nama":"Jadi Mulyo"},{"id":1804030017,"id_kecamatan":"1804030","nama":"Mekar Sari"}]