[{"id":1806072001,"id_kecamatan":"1806072","nama":"Kota Napal"},{"id":1806072002,"id_kecamatan":"1806072","nama":"Tanah Abang"},{"id":1806072003,"id_kecamatan":"1806072","nama":"Negara Tulang Bawang"},{"id":1806072004,"id_kecamatan":"1806072","nama":"Tulang Bawang Baru"},{"id":1806072005,"id_kecamatan":"1806072","nama":"Sukadana Ilir"},{"id":1806072006,"id_kecamatan":"1806072","nama":"Sukadana Udik"},{"id":1806072007,"id_kecamatan":"1806072","nama":"Haduyang Ratu"},{"id":1806072008,"id_kecamatan":"1806072","nama":"Isorejo"},{"id":1806072009,"id_kecamatan":"1806072","nama":"Mulyo Rejo Ii"},{"id":1806072010,"id_kecamatan":"1806072","nama":"Mulyo Rejo I"},{"id":1806072011,"id_kecamatan":"1806072","nama":"Sukamaju"}]