[{"id":3201030001,"id_kecamatan":"3201030","nama":"Cibunian"},{"id":3201030002,"id_kecamatan":"3201030","nama":"Purwabakti"},{"id":3201030003,"id_kecamatan":"3201030","nama":"Ciasmara"},{"id":3201030004,"id_kecamatan":"3201030","nama":"Ciasihan"},{"id":3201030005,"id_kecamatan":"3201030","nama":"Gunung Sari"},{"id":3201030008,"id_kecamatan":"3201030","nama":"Cibening"},{"id":3201030009,"id_kecamatan":"3201030","nama":"Gunung Picung"},{"id":3201030010,"id_kecamatan":"3201030","nama":"Cibitung Kulon"},{"id":3201030011,"id_kecamatan":"3201030","nama":"Cibitung Wetan"},{"id":3201030012,"id_kecamatan":"3201030","nama":"Pamijahan"},{"id":3201030013,"id_kecamatan":"3201030","nama":"Pasarean"},{"id":3201030014,"id_kecamatan":"3201030","nama":"Gunung Menyan"},{"id":3201030015,"id_kecamatan":"3201030","nama":"Cimayang"}]