[{"id":3205080001,"id_kecamatan":"3205080","nama":"Mekarsari"},{"id":3205080002,"id_kecamatan":"3205080","nama":"Karyasari"},{"id":3205080003,"id_kecamatan":"3205080","nama":"Karya Mukti"},{"id":3205080004,"id_kecamatan":"3205080","nama":"Sagara"},{"id":3205080005,"id_kecamatan":"3205080","nama":"Maroko"},{"id":3205080006,"id_kecamatan":"3205080","nama":"Sancang"},{"id":3205080007,"id_kecamatan":"3205080","nama":"Simpang"},{"id":3205080008,"id_kecamatan":"3205080","nama":"Cigaronggong"},{"id":3205080009,"id_kecamatan":"3205080","nama":"Mekarmukti"},{"id":3205080010,"id_kecamatan":"3205080","nama":"Mekarwangi"},{"id":3205080011,"id_kecamatan":"3205080","nama":"Najaten"}]