[{"id":3206010001,"id_kecamatan":"3206010","nama":"Ciheras"},{"id":3206010002,"id_kecamatan":"3206010","nama":"Cipanas"},{"id":3206010003,"id_kecamatan":"3206010","nama":"Ciandum"},{"id":3206010004,"id_kecamatan":"3206010","nama":"Cipatujah"},{"id":3206010005,"id_kecamatan":"3206010","nama":"Sindangkerta"},{"id":3206010006,"id_kecamatan":"3206010","nama":"Cikawungading"},{"id":3206010007,"id_kecamatan":"3206010","nama":"Kertasari"},{"id":3206010008,"id_kecamatan":"3206010","nama":"Padawaras"},{"id":3206010009,"id_kecamatan":"3206010","nama":"Darawati"},{"id":3206010010,"id_kecamatan":"3206010","nama":"Bantarkalong"},{"id":3206010011,"id_kecamatan":"3206010","nama":"Tobongjaya"},{"id":3206010012,"id_kecamatan":"3206010","nama":"Nangelasari"},{"id":3206010013,"id_kecamatan":"3206010","nama":"Nagrog"},{"id":3206010014,"id_kecamatan":"3206010","nama":"Pameutingan"},{"id":3206010015,"id_kecamatan":"3206010","nama":"Sukahurip"}]