[{"id":3207180001,"id_kecamatan":"3207180","nama":"Karangpari"},{"id":3207180002,"id_kecamatan":"3207180","nama":"Bojonggedang"},{"id":3207180003,"id_kecamatan":"3207180","nama":"Cisontrol"},{"id":3207180004,"id_kecamatan":"3207180","nama":"Cileungsir"},{"id":3207180005,"id_kecamatan":"3207180","nama":"Kiarapayung"},{"id":3207180006,"id_kecamatan":"3207180","nama":"Kawunglarang"},{"id":3207180007,"id_kecamatan":"3207180","nama":"Rancah"},{"id":3207180008,"id_kecamatan":"3207180","nama":"Situmandala"},{"id":3207180009,"id_kecamatan":"3207180","nama":"Patakaharja"},{"id":3207180010,"id_kecamatan":"3207180","nama":"Dadiharja"},{"id":3207180011,"id_kecamatan":"3207180","nama":"Jangalaharja"},{"id":3207180012,"id_kecamatan":"3207180","nama":"Giriharja"},{"id":3207180013,"id_kecamatan":"3207180","nama":"Wangunsari"}]