[{"id":3209121001,"id_kecamatan":"3209121","nama":"Bobos"},{"id":3209121002,"id_kecamatan":"3209121","nama":"Cikalahang"},{"id":3209121003,"id_kecamatan":"3209121","nama":"Mandala"},{"id":3209121004,"id_kecamatan":"3209121","nama":"Cisaat"},{"id":3209121005,"id_kecamatan":"3209121","nama":"Sindangjawa"},{"id":3209121006,"id_kecamatan":"3209121","nama":"Sindangmekar"},{"id":3209121007,"id_kecamatan":"3209121","nama":"Cangkoak"},{"id":3209121008,"id_kecamatan":"3209121","nama":"Kepunduan"},{"id":3209121009,"id_kecamatan":"3209121","nama":"Balad"},{"id":3209121010,"id_kecamatan":"3209121","nama":"Dukupuntang"},{"id":3209121011,"id_kecamatan":"3209121","nama":"Cipanas"},{"id":3209121012,"id_kecamatan":"3209121","nama":"Girinata"},{"id":3209121013,"id_kecamatan":"3209121","nama":"Kedongdong Kidul"}]