[{"id":3214101001,"id_kecamatan":"3214101","nama":"Maracang"},{"id":3214101002,"id_kecamatan":"3214101","nama":"Ciwareng"},{"id":3214101003,"id_kecamatan":"3214101","nama":"Mulyamekar"},{"id":3214101004,"id_kecamatan":"3214101","nama":"Cigelam"},{"id":3214101005,"id_kecamatan":"3214101","nama":"Babakancikao"},{"id":3214101006,"id_kecamatan":"3214101","nama":"Kadumekar"},{"id":3214101007,"id_kecamatan":"3214101","nama":"Hegarmanah"},{"id":3214101008,"id_kecamatan":"3214101","nama":"Cicadas"},{"id":3214101009,"id_kecamatan":"3214101","nama":"Cilangkap"}]