[{"id":3313130001,"id_kecamatan":"3313130","nama":"Wonorejo"},{"id":3313130002,"id_kecamatan":"3313130","nama":"Plesungan"},{"id":3313130003,"id_kecamatan":"3313130","nama":"Jatikuwung"},{"id":3313130004,"id_kecamatan":"3313130","nama":"Selokaton"},{"id":3313130005,"id_kecamatan":"3313130","nama":"Bulurejo"},{"id":3313130006,"id_kecamatan":"3313130","nama":"Rejosari"},{"id":3313130007,"id_kecamatan":"3313130","nama":"Jeruksawit"},{"id":3313130008,"id_kecamatan":"3313130","nama":"Karangturi"},{"id":3313130009,"id_kecamatan":"3313130","nama":"Kragan"},{"id":3313130010,"id_kecamatan":"3313130","nama":"Wonosari"},{"id":3313130011,"id_kecamatan":"3313130","nama":"Dayu"},{"id":3313130012,"id_kecamatan":"3313130","nama":"Tuban"},{"id":3313130013,"id_kecamatan":"3313130","nama":"Krendowahono"}]