[{"id":3315090001,"id_kecamatan":"3315090","nama":"Sendangrejo"},{"id":3315090002,"id_kecamatan":"3315090","nama":"Sarirejo"},{"id":3315090003,"id_kecamatan":"3315090","nama":"Kalangdosari"},{"id":3315090004,"id_kecamatan":"3315090","nama":"Kalanglundo"},{"id":3315090005,"id_kecamatan":"3315090","nama":"Truwolu"},{"id":3315090007,"id_kecamatan":"3315090","nama":"Bandungsari"},{"id":3315090008,"id_kecamatan":"3315090","nama":"Ngaringan"},{"id":3315090009,"id_kecamatan":"3315090","nama":"Ngaraparap"},{"id":3315090010,"id_kecamatan":"3315090","nama":"Belor"},{"id":3315090011,"id_kecamatan":"3315090","nama":"Tanjungharjo"},{"id":3315090012,"id_kecamatan":"3315090","nama":"Sumberagung"}]