[{"id":3315150001,"id_kecamatan":"3315150","nama":"Kandangrejo"},{"id":3315150002,"id_kecamatan":"3315150","nama":"Selojari"},{"id":3315150003,"id_kecamatan":"3315150","nama":"Taruman"},{"id":3315150004,"id_kecamatan":"3315150","nama":"Penganten"},{"id":3315150005,"id_kecamatan":"3315150","nama":"Klambu"},{"id":3315150006,"id_kecamatan":"3315150","nama":"Menawan"},{"id":3315150007,"id_kecamatan":"3315150","nama":"Terkesi"},{"id":3315150008,"id_kecamatan":"3315150","nama":"Jenengan"},{"id":3315150009,"id_kecamatan":"3315150","nama":"Wandankemiri"}]