[{"id":3319010001,"id_kecamatan":"3319010","nama":"Blimbing Kidul"},{"id":3319010002,"id_kecamatan":"3319010","nama":"Banget"},{"id":3319010003,"id_kecamatan":"3319010","nama":"Setrokalangan"},{"id":3319010004,"id_kecamatan":"3319010","nama":"Garung Kidul"},{"id":3319010005,"id_kecamatan":"3319010","nama":"Kedung Dowo"},{"id":3319010006,"id_kecamatan":"3319010","nama":"Gamong"},{"id":3319010007,"id_kecamatan":"3319010","nama":"Sidorekso"},{"id":3319010008,"id_kecamatan":"3319010","nama":"Papringan"},{"id":3319010009,"id_kecamatan":"3319010","nama":"Kaliwungu"},{"id":3319010010,"id_kecamatan":"3319010","nama":"Mijen"},{"id":3319010011,"id_kecamatan":"3319010","nama":"Karang Ampel"},{"id":3319010012,"id_kecamatan":"3319010","nama":"Garung Lor"},{"id":3319010013,"id_kecamatan":"3319010","nama":"Prambatan Lor"},{"id":3319010014,"id_kecamatan":"3319010","nama":"Prambatan Kidul"},{"id":3319010015,"id_kecamatan":"3319010","nama":"Bakalan Krapyak"}]