[{"id":3320100001,"id_kecamatan":"3320100","nama":"Guyangan"},{"id":3320100003,"id_kecamatan":"3320100","nama":"Papasan"},{"id":3320100009,"id_kecamatan":"3320100","nama":"Srikandang"},{"id":3320100010,"id_kecamatan":"3320100","nama":"Tengguli"},{"id":3320100011,"id_kecamatan":"3320100","nama":"Bangsri"},{"id":3320100012,"id_kecamatan":"3320100","nama":"Banjaran"},{"id":3320100014,"id_kecamatan":"3320100","nama":"Wedelan"},{"id":3320100015,"id_kecamatan":"3320100","nama":"Jerukwangi"},{"id":3320100022,"id_kecamatan":"3320100","nama":"Bondo"},{"id":3320100023,"id_kecamatan":"3320100","nama":"Banjar Agung"}]