[{"id":3325090004,"id_kecamatan":"3325090","nama":"Menjangan"},{"id":3325090005,"id_kecamatan":"3325090","nama":"Karangtengah"},{"id":3325090006,"id_kecamatan":"3325090","nama":"Mangunharjo"},{"id":3325090007,"id_kecamatan":"3325090","nama":"Tenggulangharjo"},{"id":3325090008,"id_kecamatan":"3325090","nama":"Keborangan"},{"id":3325090009,"id_kecamatan":"3325090","nama":"Kalimanggis"},{"id":3325090010,"id_kecamatan":"3325090","nama":"Jatisari"},{"id":3325090011,"id_kecamatan":"3325090","nama":"Subah"},{"id":3325090012,"id_kecamatan":"3325090","nama":"Kumejing"},{"id":3325090014,"id_kecamatan":"3325090","nama":"Durenombo"},{"id":3325090019,"id_kecamatan":"3325090","nama":"Clapar"},{"id":3325090021,"id_kecamatan":"3325090","nama":"Sengon"},{"id":3325090022,"id_kecamatan":"3325090","nama":"Adinuso"},{"id":3325090023,"id_kecamatan":"3325090","nama":"Gondang"},{"id":3325090024,"id_kecamatan":"3325090","nama":"Kuripan"},{"id":3325090026,"id_kecamatan":"3325090","nama":"Kemiri Barat"},{"id":3325090027,"id_kecamatan":"3325090","nama":"Kemiri Timur"}]