[{"id":3329110001,"id_kecamatan":"3329110","nama":"Sarireja"},{"id":3329110002,"id_kecamatan":"3329110","nama":"Kubangputat"},{"id":3329110005,"id_kecamatan":"3329110","nama":"Luwungbata"},{"id":3329110006,"id_kecamatan":"3329110","nama":"Karangreja"},{"id":3329110007,"id_kecamatan":"3329110","nama":"Sidakaton"},{"id":3329110008,"id_kecamatan":"3329110","nama":"Sengon"},{"id":3329110009,"id_kecamatan":"3329110","nama":"Kedawung"},{"id":3329110010,"id_kecamatan":"3329110","nama":"Tegongan"},{"id":3329110011,"id_kecamatan":"3329110","nama":"Kemurang Wetan"},{"id":3329110012,"id_kecamatan":"3329110","nama":"Kemurang Kulon"},{"id":3329110013,"id_kecamatan":"3329110","nama":"Krakahan"},{"id":3329110014,"id_kecamatan":"3329110","nama":"Pejagan"},{"id":3329110015,"id_kecamatan":"3329110","nama":"Pengaradan"},{"id":3329110016,"id_kecamatan":"3329110","nama":"Tanjung"},{"id":3329110017,"id_kecamatan":"3329110","nama":"Lemah Abang"},{"id":3329110018,"id_kecamatan":"3329110","nama":"Tengguli"}]