[{"id":3329060001,"id_kecamatan":"3329060","nama":"Kalijurang"},{"id":3329060002,"id_kecamatan":"3329060","nama":"Galuh Timur"},{"id":3329060003,"id_kecamatan":"3329060","nama":"Kutamendala"},{"id":3329060004,"id_kecamatan":"3329060","nama":"Karangjongkeng"},{"id":3329060005,"id_kecamatan":"3329060","nama":"Tonjong"},{"id":3329060006,"id_kecamatan":"3329060","nama":"Pepedan"},{"id":3329060007,"id_kecamatan":"3329060","nama":"Linggapura"},{"id":3329060008,"id_kecamatan":"3329060","nama":"Negarayu"},{"id":3329060009,"id_kecamatan":"3329060","nama":"Tanggeran"},{"id":3329060010,"id_kecamatan":"3329060","nama":"Purwodadi"},{"id":3329060011,"id_kecamatan":"3329060","nama":"Purbayasa"},{"id":3329060012,"id_kecamatan":"3329060","nama":"Watujaya"},{"id":3329060013,"id_kecamatan":"3329060","nama":"Kutayu"},{"id":3329060014,"id_kecamatan":"3329060","nama":"Rajawetan"}]