[{"id":3513240001,"id_kecamatan":"3513240","nama":"Muneng Kidul"},{"id":3513240002,"id_kecamatan":"3513240","nama":"Pohsangit Leres"},{"id":3513240003,"id_kecamatan":"3513240","nama":"Laweyan"},{"id":3513240005,"id_kecamatan":"3513240","nama":"Jangur"},{"id":3513240006,"id_kecamatan":"3513240","nama":"Sumberbendo"},{"id":3513240007,"id_kecamatan":"3513240","nama":"Mentor"},{"id":3513240008,"id_kecamatan":"3513240","nama":"Sumurmati"},{"id":3513240009,"id_kecamatan":"3513240","nama":"Pesisir"},{"id":3513240010,"id_kecamatan":"3513240","nama":"Lemahkembar"},{"id":3513240011,"id_kecamatan":"3513240","nama":"Ambulu"},{"id":3513240012,"id_kecamatan":"3513240","nama":"Banjarsari"},{"id":3513240013,"id_kecamatan":"3513240","nama":"Gili Ketapang"}]