[{"id":3519150002,"id_kecamatan":"3519150","nama":"Sambirejo"},{"id":3519150003,"id_kecamatan":"3519150","nama":"Metesih"},{"id":3519150004,"id_kecamatan":"3519150","nama":"Jiwan"},{"id":3519150005,"id_kecamatan":"3519150","nama":"Sukolilo"},{"id":3519150006,"id_kecamatan":"3519150","nama":"Kincang Wetan"},{"id":3519150007,"id_kecamatan":"3519150","nama":"Kwangsen"},{"id":3519150008,"id_kecamatan":"3519150","nama":"Grobogan"},{"id":3519150009,"id_kecamatan":"3519150","nama":"Wayut"},{"id":3519150010,"id_kecamatan":"3519150","nama":"Klagen Serut"},{"id":3519150011,"id_kecamatan":"3519150","nama":"Teguhan"},{"id":3519150013,"id_kecamatan":"3519150","nama":"Bedoho"},{"id":3519150014,"id_kecamatan":"3519150","nama":"Bibrik"}]