[{"id":3520060009,"id_kecamatan":"3520060","nama":"Ringinagung"},{"id":3520060013,"id_kecamatan":"3520060","nama":"Candirejo"},{"id":3520060014,"id_kecamatan":"3520060","nama":"Selosari"},{"id":3520060015,"id_kecamatan":"3520060","nama":"Magetan"},{"id":3520060016,"id_kecamatan":"3520060","nama":"Bulukerto"},{"id":3520060017,"id_kecamatan":"3520060","nama":"Mangkujayan"},{"id":3520060018,"id_kecamatan":"3520060","nama":"Tambakrejo"},{"id":3520060019,"id_kecamatan":"3520060","nama":"Tambran"},{"id":3520060020,"id_kecamatan":"3520060","nama":"Kebonagung"},{"id":3520060021,"id_kecamatan":"3520060","nama":"Kepolorejo"},{"id":3520060022,"id_kecamatan":"3520060","nama":"Tawanganom"},{"id":3520060023,"id_kecamatan":"3520060","nama":"Sukowinangun"},{"id":3520060024,"id_kecamatan":"3520060","nama":"Baron"},{"id":3520060025,"id_kecamatan":"3520060","nama":"Purwosari"}]