[{"id":3522080001,"id_kecamatan":"3522080","nama":"Babad"},{"id":3522080002,"id_kecamatan":"3522080","nama":"Pejok"},{"id":3522080003,"id_kecamatan":"3522080","nama":"Dayukidul"},{"id":3522080004,"id_kecamatan":"3522080","nama":"Panjang"},{"id":3522080005,"id_kecamatan":"3522080","nama":"Tondomulo"},{"id":3522080006,"id_kecamatan":"3522080","nama":"Kesongo"},{"id":3522080008,"id_kecamatan":"3522080","nama":"Mlideg"},{"id":3522080009,"id_kecamatan":"3522080","nama":"Tumbrasanom"},{"id":3522080010,"id_kecamatan":"3522080","nama":"Kedungadem"},{"id":3522080012,"id_kecamatan":"3522080","nama":"Kepoh Kidul"},{"id":3522080014,"id_kecamatan":"3522080","nama":"Kedungrejo"},{"id":3522080015,"id_kecamatan":"3522080","nama":"Megale"},{"id":3522080016,"id_kecamatan":"3522080","nama":"Sidorejo"},{"id":3522080017,"id_kecamatan":"3522080","nama":"Drokilo"},{"id":3522080018,"id_kecamatan":"3522080","nama":"Mojorejo"},{"id":3522080019,"id_kecamatan":"3522080","nama":"Jamberejo"},{"id":3522080020,"id_kecamatan":"3522080","nama":"Sidomulyo"},{"id":3522080021,"id_kecamatan":"3522080","nama":"Tlogoagung"},{"id":3522080022,"id_kecamatan":"3522080","nama":"Ngrandu"},{"id":3522080023,"id_kecamatan":"3522080","nama":"Balongcabe"}]