[{"id":3601131001,"id_kecamatan":"3601131","nama":"Karyautama"},{"id":3601131002,"id_kecamatan":"3601131","nama":"Tegal"},{"id":3601131003,"id_kecamatan":"3601131","nama":"Cipicung"},{"id":3601131004,"id_kecamatan":"3601131","nama":"Karyasari"},{"id":3601131005,"id_kecamatan":"3601131","nama":"Dahu"},{"id":3601131006,"id_kecamatan":"3601131","nama":"Babakanlor"},{"id":3601131007,"id_kecamatan":"3601131","nama":"Mekarjaya"},{"id":3601131008,"id_kecamatan":"3601131","nama":"Padahayu"},{"id":3601131009,"id_kecamatan":"3601131","nama":"Bangkuyung"},{"id":3601131010,"id_kecamatan":"3601131","nama":"Cening"}]