[{"id":3604220001,"id_kecamatan":"3604220","nama":"Lebakwana"},{"id":3604220002,"id_kecamatan":"3604220","nama":"Pelamunan"},{"id":3604220003,"id_kecamatan":"3604220","nama":"Margasana"},{"id":3604220004,"id_kecamatan":"3604220","nama":"Kramatwatu"},{"id":3604220005,"id_kecamatan":"3604220","nama":"Pejaten"},{"id":3604220006,"id_kecamatan":"3604220","nama":"Wanayasa"},{"id":3604220007,"id_kecamatan":"3604220","nama":"Harjatani"},{"id":3604220008,"id_kecamatan":"3604220","nama":"Serdang"},{"id":3604220009,"id_kecamatan":"3604220","nama":"Toyomerto"},{"id":3604220010,"id_kecamatan":"3604220","nama":"Pegadingan"},{"id":3604220011,"id_kecamatan":"3604220","nama":"Pamengkang"},{"id":3604220012,"id_kecamatan":"3604220","nama":"Tonjong"},{"id":3604220013,"id_kecamatan":"3604220","nama":"Terate"},{"id":3604220014,"id_kecamatan":"3604220","nama":"Teluk Terate"},{"id":3604220015,"id_kecamatan":"3604220","nama":"Margatani"}]