[{"id":5102070001,"id_kecamatan":"5102070","nama":"Rejasa"},{"id":5102070003,"id_kecamatan":"5102070","nama":"Riang Gede"},{"id":5102070004,"id_kecamatan":"5102070","nama":"Buruan"},{"id":5102070005,"id_kecamatan":"5102070","nama":"Tajen"},{"id":5102070006,"id_kecamatan":"5102070","nama":"Pitra"},{"id":5102070007,"id_kecamatan":"5102070","nama":"Penatahan"},{"id":5102070008,"id_kecamatan":"5102070","nama":"Tengkudak"},{"id":5102070011,"id_kecamatan":"5102070","nama":"Biaung"},{"id":5102070012,"id_kecamatan":"5102070","nama":"Babahan"},{"id":5102070013,"id_kecamatan":"5102070","nama":"Senganan"},{"id":5102070014,"id_kecamatan":"5102070","nama":"Jatiluwih"},{"id":5102070015,"id_kecamatan":"5102070","nama":"Wongaya Gede"},{"id":5102070016,"id_kecamatan":"5102070","nama":"Pesagi"},{"id":5102070017,"id_kecamatan":"5102070","nama":"Tegalinggah"},{"id":5102070018,"id_kecamatan":"5102070","nama":"Sangketan"}]