[{"id":5307050001,"id_kecamatan":"5307050","nama":"Teluk Kenari"},{"id":5307050002,"id_kecamatan":"5307050","nama":"Kalabahi Barat"},{"id":5307050003,"id_kecamatan":"5307050","nama":"Adang Buom"},{"id":5307050004,"id_kecamatan":"5307050","nama":"Binongko"},{"id":5307050005,"id_kecamatan":"5307050","nama":"Motongbang"},{"id":5307050006,"id_kecamatan":"5307050","nama":"Kalabahi Kota"},{"id":5307050007,"id_kecamatan":"5307050","nama":"Wetabua"},{"id":5307050008,"id_kecamatan":"5307050","nama":"Nusa Kenari"},{"id":5307050009,"id_kecamatan":"5307050","nama":"Lendola"},{"id":5307050010,"id_kecamatan":"5307050","nama":"Air Kenari"},{"id":5307050011,"id_kecamatan":"5307050","nama":"Kalabahi Tengah"},{"id":5307050012,"id_kecamatan":"5307050","nama":"Kalabahi Timur"},{"id":5307050013,"id_kecamatan":"5307050","nama":"Mutiara"},{"id":5307050017,"id_kecamatan":"5307050","nama":"Welai Timur"},{"id":5307050020,"id_kecamatan":"5307050","nama":"Welai Barat"},{"id":5307050021,"id_kecamatan":"5307050","nama":"Fanating"}]