[{"id":5309010001,"id_kecamatan":"5309010","nama":"Ojan Detun"},{"id":5309010002,"id_kecamatan":"5309010","nama":"Hewa"},{"id":5309010003,"id_kecamatan":"5309010","nama":"Pantai Oa"},{"id":5309010004,"id_kecamatan":"5309010","nama":"Waiula"},{"id":5309010009,"id_kecamatan":"5309010","nama":"Nawokote"},{"id":5309010010,"id_kecamatan":"5309010","nama":"Boru Kedang"},{"id":5309010011,"id_kecamatan":"5309010","nama":"Boru"},{"id":5309010012,"id_kecamatan":"5309010","nama":"Hokeng Jaya"},{"id":5309010014,"id_kecamatan":"5309010","nama":"Pululera"},{"id":5309010015,"id_kecamatan":"5309010","nama":"Nileknoheng"},{"id":5309010016,"id_kecamatan":"5309010","nama":"Klatanlo"}]