[{"id":5312081001,"id_kecamatan":"5312081","nama":"Wolomeze"},{"id":5312081002,"id_kecamatan":"5312081","nama":"Ria"},{"id":5312081003,"id_kecamatan":"5312081","nama":"Lanamai"},{"id":5312081004,"id_kecamatan":"5312081","nama":"Benteng Tawa"},{"id":5312081005,"id_kecamatan":"5312081","nama":"Ngara"},{"id":5312081006,"id_kecamatan":"5312081","nama":"Ria I"},{"id":5312081007,"id_kecamatan":"5312081","nama":"Wolomeze I"},{"id":5312081008,"id_kecamatan":"5312081","nama":"Lanamai I"},{"id":5312081009,"id_kecamatan":"5312081","nama":"Benteng Tawa I"},{"id":5312081010,"id_kecamatan":"5312081","nama":"Wolomeze Ii"}]