[{"id":5317060001,"id_kecamatan":"5317060","nama":"Dangga Mango"},{"id":5317060002,"id_kecamatan":"5317060","nama":"Dikira"},{"id":5317060003,"id_kecamatan":"5317060","nama":"Pada Ewata"},{"id":5317060004,"id_kecamatan":"5317060","nama":"Mareda Kalada"},{"id":5317060005,"id_kecamatan":"5317060","nama":"Tema Tana"},{"id":5317060007,"id_kecamatan":"5317060","nama":"Kalembu Ndara Mane"},{"id":5317060017,"id_kecamatan":"5317060","nama":"Weelimbu"},{"id":5317060018,"id_kecamatan":"5317060","nama":"Letekamouna"},{"id":5317060019,"id_kecamatan":"5317060","nama":"Mata Pyawu"},{"id":5317060020,"id_kecamatan":"5317060","nama":"Wee Lima"},{"id":5317060021,"id_kecamatan":"5317060","nama":"Kadi Wone"},{"id":5317060022,"id_kecamatan":"5317060","nama":"Maliti Dari"},{"id":5317060023,"id_kecamatan":"5317060","nama":"Dede Pada"},{"id":5317060024,"id_kecamatan":"5317060","nama":"Kadi Wano"},{"id":5317060025,"id_kecamatan":"5317060","nama":"Nyura Lele"},{"id":5317060026,"id_kecamatan":"5317060","nama":"Mawo Dana"},{"id":5317060027,"id_kecamatan":"5317060","nama":"Mainda Ole"},{"id":5317060028,"id_kecamatan":"5317060","nama":"Lele Maya"},{"id":5317060029,"id_kecamatan":"5317060","nama":"Mata Wee Lima"}]