[{"id":5319050001,"id_kecamatan":"5319050","nama":"Golo Lobos"},{"id":5319050002,"id_kecamatan":"5319050","nama":"Bangka Kuleng"},{"id":5319050003,"id_kecamatan":"5319050","nama":"Mando Sawu"},{"id":5319050004,"id_kecamatan":"5319050","nama":"Bangka Pau"},{"id":5319050005,"id_kecamatan":"5319050","nama":"Nggalak Leleng"},{"id":5319050006,"id_kecamatan":"5319050","nama":"Golo Nderu"},{"id":5319050007,"id_kecamatan":"5319050","nama":"Pocolia"},{"id":5319050016,"id_kecamatan":"5319050","nama":"Gurung Turi"},{"id":5319050017,"id_kecamatan":"5319050","nama":"Compang Laho"},{"id":5319050018,"id_kecamatan":"5319050","nama":"Bea Waek"},{"id":5319050019,"id_kecamatan":"5319050","nama":"Satar Tesem"},{"id":5319050020,"id_kecamatan":"5319050","nama":"Lenang"},{"id":5319050021,"id_kecamatan":"5319050","nama":"Pocong"},{"id":5319050025,"id_kecamatan":"5319050","nama":"Watu Lanur"},{"id":5319050026,"id_kecamatan":"5319050","nama":"Leong"},{"id":5319050027,"id_kecamatan":"5319050","nama":"Melo"},{"id":5319050028,"id_kecamatan":"5319050","nama":"Golo Ndari"},{"id":5319050029,"id_kecamatan":"5319050","nama":"Compang Wesang"},{"id":5319050030,"id_kecamatan":"5319050","nama":"Bangka Leleng"},{"id":5319050031,"id_kecamatan":"5319050","nama":"Lento"},{"id":5319050036,"id_kecamatan":"5319050","nama":"Golo Rengket"},{"id":5319050037,"id_kecamatan":"5319050","nama":"Golo Wune"},{"id":5319050038,"id_kecamatan":"5319050","nama":"Deno"},{"id":5319050041,"id_kecamatan":"5319050","nama":"Compang Weluk"}]