[{"id":6306030001,"id_kecamatan":"6306030","nama":"Ambutun"},{"id":6306030003,"id_kecamatan":"6306030","nama":"Lok Binuang"},{"id":6306030004,"id_kecamatan":"6306030","nama":"Telaga Langsat"},{"id":6306030005,"id_kecamatan":"6306030","nama":"Mandala"},{"id":6306030008,"id_kecamatan":"6306030","nama":"Pakuan Timur"},{"id":6306030010,"id_kecamatan":"6306030","nama":"Pandulangan"},{"id":6306030011,"id_kecamatan":"6306030","nama":"Longawang"},{"id":6306030012,"id_kecamatan":"6306030","nama":"Gumbil"},{"id":6306030014,"id_kecamatan":"6306030","nama":"Hamak"},{"id":6306030015,"id_kecamatan":"6306030","nama":"Hamak Timur"},{"id":6306030016,"id_kecamatan":"6306030","nama":"Hamak Utara"}]