[{"id":6307060002,"id_kecamatan":"6307060","nama":"Panggang Marak"},{"id":6307060004,"id_kecamatan":"6307060","nama":"Mundar"},{"id":6307060007,"id_kecamatan":"6307060","nama":"Tabudarat Hilir"},{"id":6307060008,"id_kecamatan":"6307060","nama":"Baru"},{"id":6307060010,"id_kecamatan":"6307060","nama":"Jamil"},{"id":6307060011,"id_kecamatan":"6307060","nama":"Tabudarat Hulu"},{"id":6307060013,"id_kecamatan":"6307060","nama":"Pantai Hambawang Barat"},{"id":6307060014,"id_kecamatan":"6307060","nama":"Pantai Hambawang Timur"},{"id":6307060017,"id_kecamatan":"6307060","nama":"Benua Kepayang"},{"id":6307060019,"id_kecamatan":"6307060","nama":"Sungai Jaranih"},{"id":6307060021,"id_kecamatan":"6307060","nama":"Batang Bahalang"},{"id":6307060022,"id_kecamatan":"6307060","nama":"Taal"},{"id":6307060024,"id_kecamatan":"6307060","nama":"Murung Taal"},{"id":6307060027,"id_kecamatan":"6307060","nama":"Sungai Rangas"},{"id":6307060029,"id_kecamatan":"6307060","nama":"Durian Gantang"},{"id":6307060032,"id_kecamatan":"6307060","nama":"Guha"},{"id":6307060033,"id_kecamatan":"6307060","nama":"Bangkal"},{"id":6307060035,"id_kecamatan":"6307060","nama":"Taras Padang"}]