[{"id":7109062001,"id_kecamatan":"7109062","nama":"Silian Dua"},{"id":7109062002,"id_kecamatan":"7109062","nama":"Silian Tengah"},{"id":7109062003,"id_kecamatan":"7109062","nama":"Silian Kota"},{"id":7109062004,"id_kecamatan":"7109062","nama":"Silian Satu"},{"id":7109062005,"id_kecamatan":"7109062","nama":"Silian Selatan"},{"id":7109062006,"id_kecamatan":"7109062","nama":"Silian Tiga"},{"id":7109062007,"id_kecamatan":"7109062","nama":"Silian Barat"},{"id":7109062008,"id_kecamatan":"7109062","nama":"Silian"},{"id":7109062009,"id_kecamatan":"7109062","nama":"Silian Utara"},{"id":7109062010,"id_kecamatan":"7109062","nama":"Silian Timur"}]