[{"id":7110030001,"id_kecamatan":"7110030","nama":"Linawan"},{"id":7110030002,"id_kecamatan":"7110030","nama":"Linawan I"},{"id":7110030004,"id_kecamatan":"7110030","nama":"Ilomata"},{"id":7110030005,"id_kecamatan":"7110030","nama":"Pinolosian Selatan"},{"id":7110030006,"id_kecamatan":"7110030","nama":"Pinolosian"},{"id":7110030007,"id_kecamatan":"7110030","nama":"Tolotoyon"},{"id":7110030008,"id_kecamatan":"7110030","nama":"Kombot"},{"id":7110030009,"id_kecamatan":"7110030","nama":"Lungkap"},{"id":7110030010,"id_kecamatan":"7110030","nama":"Kombot Timur"}]