[{"id":7307010001,"id_kecamatan":"7307010","nama":"Gunung Perak"},{"id":7307010002,"id_kecamatan":"7307010","nama":"Balakia"},{"id":7307010003,"id_kecamatan":"7307010","nama":"Tassililu"},{"id":7307010004,"id_kecamatan":"7307010","nama":"Arabika"},{"id":7307010005,"id_kecamatan":"7307010","nama":"Barania"},{"id":7307010006,"id_kecamatan":"7307010","nama":"Boto Lempangan"},{"id":7307010007,"id_kecamatan":"7307010","nama":"Bonto Salama"},{"id":7307010008,"id_kecamatan":"7307010","nama":"Turungan Baji"},{"id":7307010009,"id_kecamatan":"7307010","nama":"Terasa"}]