[{"id":7315010001,"id_kecamatan":"7315010","nama":"Lero"},{"id":7315010002,"id_kecamatan":"7315010","nama":"Ujung Labuang"},{"id":7315010003,"id_kecamatan":"7315010","nama":"Wiringtasi"},{"id":7315010004,"id_kecamatan":"7315010","nama":"Tasiwalie"},{"id":7315010005,"id_kecamatan":"7315010","nama":"Maritengngae"},{"id":7315010006,"id_kecamatan":"7315010","nama":"Watang Suppa"},{"id":7315010007,"id_kecamatan":"7315010","nama":"Tellumpanua"},{"id":7315010008,"id_kecamatan":"7315010","nama":"Wattang Pulu"},{"id":7315010009,"id_kecamatan":"7315010","nama":"Polewali"},{"id":7315010010,"id_kecamatan":"7315010","nama":"Lotang Salo"}]