[{"id":7326170001,"id_kecamatan":"7326170","nama":"Lembang Kapoloang"},{"id":7326170002,"id_kecamatan":"7326170","nama":"Lembang Piongan"},{"id":7326170003,"id_kecamatan":"7326170","nama":"Kelurahan Pasang"},{"id":7326170004,"id_kecamatan":"7326170","nama":"Lembang Dende"},{"id":7326170005,"id_kecamatan":"7326170","nama":"Lembang Paku"},{"id":7326170006,"id_kecamatan":"7326170","nama":"Lembang Ma'dong"},{"id":7326170007,"id_kecamatan":"7326170","nama":"Lembang Buntu Tagari"},{"id":7326170008,"id_kecamatan":"7326170","nama":"Lembang Parindingan"}]