[{"id":7403185001,"id_kecamatan":"7403185","nama":"Andalambe"},{"id":7403185002,"id_kecamatan":"7403185","nama":"Waworoda Jaya"},{"id":7403185003,"id_kecamatan":"7403185","nama":"Sanuanggamo"},{"id":7403185004,"id_kecamatan":"7403185","nama":"Olo Onua"},{"id":7403185005,"id_kecamatan":"7403185","nama":"Puudombi"},{"id":7403185006,"id_kecamatan":"7403185","nama":"Oluaao"},{"id":7403185007,"id_kecamatan":"7403185","nama":"Anggohu"},{"id":7403185008,"id_kecamatan":"7403185","nama":"Ambopi"},{"id":7403185009,"id_kecamatan":"7403185","nama":"Barowila"},{"id":7403185010,"id_kecamatan":"7403185","nama":"Nambeaboru"}]