[{"id":7404070010,"id_kecamatan":"7404070","nama":"Donggala"},{"id":7404070011,"id_kecamatan":"7404070","nama":"Ulu Lapao-pao"},{"id":7404070012,"id_kecamatan":"7404070","nama":"Lapao-pao"},{"id":7404070013,"id_kecamatan":"7404070","nama":"Tolowe Ponre Waru"},{"id":7404070014,"id_kecamatan":"7404070","nama":"Langgomali"},{"id":7404070015,"id_kecamatan":"7404070","nama":"Ulu Wolo"},{"id":7404070016,"id_kecamatan":"7404070","nama":"Wolo"},{"id":7404070017,"id_kecamatan":"7404070","nama":"Lalonaha"},{"id":7404070018,"id_kecamatan":"7404070","nama":"L A N A"},{"id":7404070024,"id_kecamatan":"7404070","nama":"Muara Lapao Pao"},{"id":7404070025,"id_kecamatan":"7404070","nama":"Lalonggopi"},{"id":7404070027,"id_kecamatan":"7404070","nama":"Samaenre"},{"id":7404070028,"id_kecamatan":"7404070","nama":"Iwoimapuro"},{"id":7404070029,"id_kecamatan":"7404070","nama":"Ulu Rina"}]