[{"id":7410060001,"id_kecamatan":"7410060","nama":"Sari Mukti (upt.hialu Iv)"},{"id":7410060002,"id_kecamatan":"7410060","nama":"Langgi Kima (upt.hialu Iii)"},{"id":7410060003,"id_kecamatan":"7410060","nama":"Molore"},{"id":7410060004,"id_kecamatan":"7410060","nama":"Lameruru"},{"id":7410060005,"id_kecamatan":"7410060","nama":"Upt.morombo\/tobimeita"},{"id":7410060006,"id_kecamatan":"7410060","nama":"Pariama"},{"id":7410060007,"id_kecamatan":"7410060","nama":"Polora Indah"},{"id":7410060008,"id_kecamatan":"7410060","nama":"Alenggo"},{"id":7410060009,"id_kecamatan":"7410060","nama":"Mekar Jaya"},{"id":7410060010,"id_kecamatan":"7410060","nama":"Molore Pantai"},{"id":7410060011,"id_kecamatan":"7410060","nama":"Ngapainia"},{"id":7410060012,"id_kecamatan":"7410060","nama":"Morombo Pantai"}]