[{"id":8272050003,"id_kecamatan":"8272050","nama":"Somahode"},{"id":8272050004,"id_kecamatan":"8272050","nama":"Akekolano"},{"id":8272050005,"id_kecamatan":"8272050","nama":"Oba"},{"id":8272050006,"id_kecamatan":"8272050","nama":"Sofifi"},{"id":8272050007,"id_kecamatan":"8272050","nama":"Guraping"},{"id":8272050008,"id_kecamatan":"8272050","nama":"Kaiyasa"},{"id":8272050009,"id_kecamatan":"8272050","nama":"Garojou"},{"id":8272050011,"id_kecamatan":"8272050","nama":"Ampera"},{"id":8272050012,"id_kecamatan":"8272050","nama":"Bukit Durian"},{"id":8272050013,"id_kecamatan":"8272050","nama":"Galala"},{"id":8272050014,"id_kecamatan":"8272050","nama":"Balbar"},{"id":8272050015,"id_kecamatan":"8272050","nama":"Gosale"}]