[{"id":9408060010,"id_kecamatan":"9408060","nama":"Banawa"},{"id":9408060011,"id_kecamatan":"9408060","nama":"Serui Laut"},{"id":9408060012,"id_kecamatan":"9408060","nama":"Pasir Putih"},{"id":9408060013,"id_kecamatan":"9408060","nama":"Pasir Hitam"},{"id":9408060014,"id_kecamatan":"9408060","nama":"Tarau"},{"id":9408060015,"id_kecamatan":"9408060","nama":"Serui Kota"},{"id":9408060016,"id_kecamatan":"9408060","nama":"Serui Jaya"},{"id":9408060026,"id_kecamatan":"9408060","nama":"Barawaikap"},{"id":9408060027,"id_kecamatan":"9408060","nama":"Nundawipi"},{"id":9408060028,"id_kecamatan":"9408060","nama":"Bawai"},{"id":9408060029,"id_kecamatan":"9408060","nama":"Manaini"},{"id":9408060030,"id_kecamatan":"9408060","nama":"Imandoa"}]