[{"id":9411071001,"id_kecamatan":"9411071","nama":"Torage"},{"id":9411071002,"id_kecamatan":"9411071","nama":"Palumagi"},{"id":9411071003,"id_kecamatan":"9411071","nama":"Jiramok"},{"id":9411071004,"id_kecamatan":"9411071","nama":"Yanenggawi"},{"id":9411071005,"id_kecamatan":"9411071","nama":"Wurabume"},{"id":9411071006,"id_kecamatan":"9411071","nama":"Binggelume"},{"id":9411071007,"id_kecamatan":"9411071","nama":"Kayogebur"},{"id":9411071008,"id_kecamatan":"9411071","nama":"Kalome"},{"id":9411071009,"id_kecamatan":"9411071","nama":"Agape"},{"id":9411071010,"id_kecamatan":"9411071","nama":"Cilome"},{"id":9411071011,"id_kecamatan":"9411071","nama":"Longgawi"},{"id":9411071012,"id_kecamatan":"9411071","nama":"Wundini"},{"id":9411071014,"id_kecamatan":"9411071","nama":"Diraluk"},{"id":9411071015,"id_kecamatan":"9411071","nama":"Pilibur"},{"id":9411071016,"id_kecamatan":"9411071","nama":"Jinggwi"}]