[{"id":9411091001,"id_kecamatan":"9411091","nama":"Dokome"},{"id":9411091002,"id_kecamatan":"9411091","nama":"Urage"},{"id":9411091003,"id_kecamatan":"9411091","nama":"Nungwawi"},{"id":9411091004,"id_kecamatan":"9411091","nama":"Nowoneri"},{"id":9411091005,"id_kecamatan":"9411091","nama":"Nowome"},{"id":9411091006,"id_kecamatan":"9411091","nama":"Imulineri"},{"id":9411091007,"id_kecamatan":"9411091","nama":"Molobak"},{"id":9411091008,"id_kecamatan":"9411091","nama":"Purbalo"},{"id":9411091009,"id_kecamatan":"9411091","nama":"Kumibut"}]