[{"id":1205030,"id_kota":"1205","nama":"Parmonangan"},{"id":1205040,"id_kota":"1205","nama":"Adiankoting"},{"id":1205050,"id_kota":"1205","nama":"Sipoholon"},{"id":1205060,"id_kota":"1205","nama":"Tarutung"},{"id":1205061,"id_kota":"1205","nama":"Siatas Barita"},{"id":1205070,"id_kota":"1205","nama":"Pahae Julu"},{"id":1205080,"id_kota":"1205","nama":"Pahae Jae"},{"id":1205081,"id_kota":"1205","nama":"Purbatua"},{"id":1205082,"id_kota":"1205","nama":"Simangumban"},{"id":1205090,"id_kota":"1205","nama":"Pangaribuan"},{"id":1205100,"id_kota":"1205","nama":"Garoga"},{"id":1205110,"id_kota":"1205","nama":"Sipahutar"},{"id":1205120,"id_kota":"1205","nama":"Siborongborong"},{"id":1205130,"id_kota":"1205","nama":"Pagaran"},{"id":1205180,"id_kota":"1205","nama":"Muara"}]