[{"id":1307010,"id_kota":"1307","nama":"Tanjung Mutiara"},{"id":1307020,"id_kota":"1307","nama":"Lubuk Basung"},{"id":1307021,"id_kota":"1307","nama":"Ampek Nagari"},{"id":1307030,"id_kota":"1307","nama":"Tanjung Raya"},{"id":1307040,"id_kota":"1307","nama":"Matur"},{"id":1307050,"id_kota":"1307","nama":"Iv Koto"},{"id":1307051,"id_kota":"1307","nama":"Malalak"},{"id":1307061,"id_kota":"1307","nama":"Banuhampu"},{"id":1307062,"id_kota":"1307","nama":"Sungai Pua"},{"id":1307070,"id_kota":"1307","nama":"Ampek Angkek"},{"id":1307071,"id_kota":"1307","nama":"Canduang"},{"id":1307080,"id_kota":"1307","nama":"Baso"},{"id":1307090,"id_kota":"1307","nama":"Tilatang Kamang"},{"id":1307091,"id_kota":"1307","nama":"Kamang Magek"},{"id":1307100,"id_kota":"1307","nama":"Palembayan"},{"id":1307110,"id_kota":"1307","nama":"Palupuh"}]