[{"id":1505010,"id_kota":"1505","nama":"Mestong"},{"id":1505011,"id_kota":"1505","nama":"Sungai Bahar"},{"id":1505012,"id_kota":"1505","nama":"Bahar Selatan"},{"id":1505013,"id_kota":"1505","nama":"Bahar Utara"},{"id":1505020,"id_kota":"1505","nama":"Kumpeh Ulu"},{"id":1505021,"id_kota":"1505","nama":"Sungai Gelam"},{"id":1505030,"id_kota":"1505","nama":"Kumpeh"},{"id":1505040,"id_kota":"1505","nama":"Maro Sebo"},{"id":1505041,"id_kota":"1505","nama":"Taman Rajo"},{"id":1505050,"id_kota":"1505","nama":"Jambi Luar Kota"},{"id":1505060,"id_kota":"1505","nama":"Sekernan"}]