[{"id":3501010,"id_kota":"3501","nama":"Donorojo"},{"id":3501020,"id_kota":"3501","nama":"Punung"},{"id":3501030,"id_kota":"3501","nama":"Pringkuku"},{"id":3501040,"id_kota":"3501","nama":"Pacitan"},{"id":3501050,"id_kota":"3501","nama":"Kebonagung"},{"id":3501060,"id_kota":"3501","nama":"Arjosari"},{"id":3501070,"id_kota":"3501","nama":"Nawangan"},{"id":3501080,"id_kota":"3501","nama":"Bandar"},{"id":3501090,"id_kota":"3501","nama":"Tegalombo"},{"id":3501100,"id_kota":"3501","nama":"Tulakan"},{"id":3501110,"id_kota":"3501","nama":"Ngadirojo"},{"id":3501120,"id_kota":"3501","nama":"Sudimoro"}]