[{"id":7503010,"id_kota":"7503","nama":"Popayato"},{"id":7503011,"id_kota":"7503","nama":"Popayato Barat"},{"id":7503012,"id_kota":"7503","nama":"Popayato Timur"},{"id":7503020,"id_kota":"7503","nama":"Lemito"},{"id":7503021,"id_kota":"7503","nama":"Wanggarasi"},{"id":7503030,"id_kota":"7503","nama":"Marisa"},{"id":7503031,"id_kota":"7503","nama":"Patilanggio"},{"id":7503032,"id_kota":"7503","nama":"Buntulia"},{"id":7503033,"id_kota":"7503","nama":"Duhiadaa"},{"id":7503040,"id_kota":"7503","nama":"Randangan"},{"id":7503041,"id_kota":"7503","nama":"Taluditi"},{"id":7503050,"id_kota":"7503","nama":"Paguat"},{"id":7503051,"id_kota":"7503","nama":"Dengilo"}]